hidapi.py
hidapi_usb-0.3.1.dist-info/LICENSE.txt
hidapi_usb-0.3.1.dist-info/METADATA
hidapi_usb-0.3.1.dist-info/WHEEL
hidapi_usb-0.3.1.dist-info/top_level.txt
hidapi_usb-0.3.1.dist-info/RECORD
