Metadata-Version: 1.0
Name: hidapi-usb
Version: 0.3.1
Summary: CFFI wrapper for hidapi with changes by flok
Home-page: https://github.com/flok/hidapi-cffi.git
Author: Florian K
Author-email: 37000563+flok@users.noreply.github.com
License: BSD
Platform: UNKNOWN
